gt_twixtools-1.0.1.data/scripts/convert_to_cfl.py
gt_twixtools-1.0.1.data/scripts/datmeta2json.py
gt_twixtools-1.0.1.data/scripts/rotate_3Dcfl.py
gt_twixtools-1.0.1.data/scripts/twixzip.py
twixtools/__init__.py
twixtools/geometry.py
twixtools/hdr_def.py
twixtools/helpers.py
twixtools/map_twix.py
twixtools/mdb.py
twixtools/mdh_def.py
twixtools/pmu.py
twixtools/quat.py
twixtools/recon_helpers.py
twixtools/twixprot.py
twixtools/twixtools.py
twixtools/twixzip.py
twixtools/contrib/cfl.py
gt_twixtools-1.0.1.dist-info/LICENSE
gt_twixtools-1.0.1.dist-info/METADATA
gt_twixtools-1.0.1.dist-info/WHEEL
gt_twixtools-1.0.1.dist-info/top_level.txt
gt_twixtools-1.0.1.dist-info/RECORD
