Metadata-Version: 2.1
Name: gt-twixtools
Version: 1.0.1
Summary: file reader for Siemens twix(.dat)-files
Home-page: https://github.com/pehses/twixtools
Author: Philipp Ehses (modified by Martin Buehrer)
Author-email: philipp.ehses@dzne.de (martin.buehrer@gyrotools.com)
License: MIT
Keywords: twix,,siemens,,mri
Requires-Python: <4,>=3.7
License-File: LICENSE
Requires-Dist: numpy
Requires-Dist: scipy
Requires-Dist: tqdm
Provides-Extra: test
Requires-Dist: pytest ; extra == 'test'
Requires-Dist: tables ; extra == 'test'
Requires-Dist: pyzfp ; extra == 'test'
